{
	"info": {
		"_postman_id": "3a801bb5-d88e-465f-922e-6fce31c27795",
		"name": "Ecommerce sails",
		"schema": "https://schema.getpostman.com/json/collection/v2.1.0/collection.json",
		"_exporter_id": "32823335"
	},
	"item": [
		{
			"name": "User",
			"item": [
				{
					"name": "login",
					"request": {
						"method": "POST",
						"header": [],
						"body": {
							"mode": "raw",
							"raw": "{\n    \"email\":\"abc@abc.com\",\n    \"password\":\"123456\"\n}",
							"options": {
								"raw": {
									"language": "json"
								}
							}
						},
						"url": {
							"raw": "http://localhost:1337/login",
							"protocol": "http",
							"host": [
								"localhost"
							],
							"port": "1337",
							"path": [
								"login"
							]
						}
					},
					"response": [
						{
							"name": "success",
							"originalRequest": {
								"method": "POST",
								"header": [],
								"body": {
									"mode": "raw",
									"raw": "{\n    \"email\":\"abc@abc.com\",\n    \"password\":\"123456\"\n}",
									"options": {
										"raw": {
											"language": "json"
										}
									}
								},
								"url": {
									"raw": "http://localhost:1337/login",
									"protocol": "http",
									"host": [
										"localhost"
									],
									"port": "1337",
									"path": [
										"login"
									]
								}
							},
							"status": "OK",
							"code": 200,
							"_postman_previewlanguage": "json",
							"header": [
								{
									"key": "X-Powered-By",
									"value": "Sails <sailsjs.com>"
								},
								{
									"key": "token",
									"value": "eyJhbGciOiJIUzI1NiIsInR5cCI6IkpXVCJ9.eyJpZCI6IjY1ZTFhMTZiMjk1ZmY3ZDY0M2MyNDg4ZCIsImVtYWlsIjoiYWJjQGFiYy5jb20iLCJzdXBlclVzZXIiOnRydWUsImlhdCI6MTcwOTU0NDQ0NiwiZXhwIjoxNzA5NjMwODQ2fQ.Gv80FBQaZFD34xRXqV-uMNgkpUiDOyo1Vu70Z7aAf_E"
								},
								{
									"key": "Set-Cookie",
									"value": "JWTtoken=eyJhbGciOiJIUzI1NiIsInR5cCI6IkpXVCJ9.eyJpZCI6IjY1ZTFhMTZiMjk1ZmY3ZDY0M2MyNDg4ZCIsImVtYWlsIjoiYWJjQGFiYy5jb20iLCJzdXBlclVzZXIiOnRydWUsImlhdCI6MTcwOTU0NDQ0NiwiZXhwIjoxNzA5NjMwODQ2fQ.Gv80FBQaZFD34xRXqV-uMNgkpUiDOyo1Vu70Z7aAf_E; Max-Age=86400; Path=/; Expires=Tue, 05 Mar 2024 09:27:26 GMT; HttpOnly"
								},
								{
									"key": "Content-Type",
									"value": "application/json; charset=utf-8"
								},
								{
									"key": "Content-Length",
									"value": "33"
								},
								{
									"key": "ETag",
									"value": "W/\"21-UJHQGX+9TIlYG3IrpydYohdunOA\""
								},
								{
									"key": "Date",
									"value": "Mon, 04 Mar 2024 09:27:26 GMT"
								},
								{
									"key": "Connection",
									"value": "keep-alive"
								},
								{
									"key": "Keep-Alive",
									"value": "timeout=5"
								}
							],
							"cookie": [],
							"body": "\"you have successfully logged in\""
						}
					]
				},
				{
					"name": "signup",
					"request": {
						"method": "POST",
						"header": [],
						"body": {
							"mode": "raw",
							"raw": "{\n    \"email\":\"mj@shah.com\",\n    \"name\":\"Mjshah\",\n    \"password\":\"123456\",\n    \"mobileno\":\"1234567890\",\n    \"address\":\"home\"\n}",
							"options": {
								"raw": {
									"language": "json"
								}
							}
						},
						"url": {
							"raw": "http://localhost:1337/signup",
							"protocol": "http",
							"host": [
								"localhost"
							],
							"port": "1337",
							"path": [
								"signup"
							]
						}
					},
					"response": [
						{
							"name": "success",
							"originalRequest": {
								"method": "POST",
								"header": [],
								"body": {
									"mode": "raw",
									"raw": "{\n    \"email\":\"mj@shah.com\",\n    \"name\":\"Mjshah\",\n    \"password\":\"123456\",\n    \"mobileno\":\"1234567890\",\n    \"address\":\"home\"\n}",
									"options": {
										"raw": {
											"language": "json"
										}
									}
								},
								"url": {
									"raw": "http://localhost:1337/signup",
									"protocol": "http",
									"host": [
										"localhost"
									],
									"port": "1337",
									"path": [
										"signup"
									]
								}
							},
							"status": "OK",
							"code": 200,
							"_postman_previewlanguage": "json",
							"header": [
								{
									"key": "X-Powered-By",
									"value": "Sails <sailsjs.com>"
								},
								{
									"key": "Content-Type",
									"value": "application/json; charset=utf-8"
								},
								{
									"key": "Content-Length",
									"value": "32"
								},
								{
									"key": "ETag",
									"value": "W/\"20-0xaTR5KqYOyq6PuDmigj5B//LfQ\""
								},
								{
									"key": "Date",
									"value": "Mon, 04 Mar 2024 09:30:29 GMT"
								},
								{
									"key": "Connection",
									"value": "keep-alive"
								},
								{
									"key": "Keep-Alive",
									"value": "timeout=5"
								}
							],
							"cookie": [],
							"body": "\"You have signed in succesfully\""
						}
					]
				},
				{
					"name": "logout",
					"request": {
						"method": "POST",
						"header": [],
						"url": {
							"raw": "http://localhost:1337/logout",
							"protocol": "http",
							"host": [
								"localhost"
							],
							"port": "1337",
							"path": [
								"logout"
							]
						}
					},
					"response": [
						{
							"name": "New Request",
							"originalRequest": {
								"method": "POST",
								"header": [],
								"url": {
									"raw": "http://localhost:1337/logout",
									"protocol": "http",
									"host": [
										"localhost"
									],
									"port": "1337",
									"path": [
										"logout"
									]
								}
							},
							"status": "Bad Request",
							"code": 400,
							"_postman_previewlanguage": "json",
							"header": [
								{
									"key": "X-Powered-By",
									"value": "Sails <sailsjs.com>"
								},
								{
									"key": "Content-Type",
									"value": "application/json; charset=utf-8"
								},
								{
									"key": "Content-Length",
									"value": "35"
								},
								{
									"key": "ETag",
									"value": "W/\"23-BsqJBy8UuB44G73YwF5+W4eai+I\""
								},
								{
									"key": "Set-Cookie",
									"value": "connect.sid=s%3AJ0-QE3pmt22hXK9agTvJg50iWSRCkk8B.AA0mFNmJs7pWI2ADbQaaeSlN5y3u8Ivrwpeb40Z%2Fgxc; Path=/; Expires=Tue, 05 Mar 2024 11:26:52 GMT; HttpOnly"
								},
								{
									"key": "Date",
									"value": "Mon, 04 Mar 2024 11:26:52 GMT"
								},
								{
									"key": "Connection",
									"value": "keep-alive"
								},
								{
									"key": "Keep-Alive",
									"value": "timeout=5"
								}
							],
							"cookie": [],
							"body": "{\n    \"error\": \"No users to logout\"\n}"
						}
					]
				}
			]
		},
		{
			"name": "Shop",
			"item": [
				{
					"name": "Cart",
					"request": {
						"method": "GET",
						"header": [],
						"url": {
							"raw": "http://localhost:1337/cart",
							"protocol": "http",
							"host": [
								"localhost"
							],
							"port": "1337",
							"path": [
								"cart"
							]
						}
					},
					"response": [
						{
							"name": "get cart",
							"originalRequest": {
								"method": "GET",
								"header": [],
								"url": {
									"raw": "http://localhost:1337/cart",
									"protocol": "http",
									"host": [
										"localhost"
									],
									"port": "1337",
									"path": [
										"cart"
									]
								}
							},
							"status": "OK",
							"code": 200,
							"_postman_previewlanguage": "json",
							"header": [
								{
									"key": "X-Powered-By",
									"value": "Sails <sailsjs.com>"
								},
								{
									"key": "Content-Type",
									"value": "application/json; charset=utf-8"
								},
								{
									"key": "Content-Length",
									"value": "2"
								},
								{
									"key": "ETag",
									"value": "W/\"2-l9Fw4VUO7kr8CvBlt4zaMCqXZ0w\""
								},
								{
									"key": "Date",
									"value": "Mon, 04 Mar 2024 09:59:22 GMT"
								},
								{
									"key": "Connection",
									"value": "keep-alive"
								},
								{
									"key": "Keep-Alive",
									"value": "timeout=5"
								}
							],
							"cookie": [],
							"body": "[]"
						}
					]
				},
				{
					"name": "Post cart",
					"request": {
						"method": "POST",
						"header": [],
						"body": {
							"mode": "raw",
							"raw": "{\n    \"productId\":\"65e59b7493605124c39f30cf\"\n}",
							"options": {
								"raw": {
									"language": "json"
								}
							}
						},
						"url": {
							"raw": "http://localhost:1337/cart",
							"protocol": "http",
							"host": [
								"localhost"
							],
							"port": "1337",
							"path": [
								"cart"
							]
						}
					},
					"response": [
						{
							"name": "success",
							"originalRequest": {
								"method": "POST",
								"header": [],
								"body": {
									"mode": "raw",
									"raw": "{\n    \"productId\":\"65e59b7493605124c39f30cf\"\n}",
									"options": {
										"raw": {
											"language": "json"
										}
									}
								},
								"url": {
									"raw": "http://localhost:1337/cart",
									"protocol": "http",
									"host": [
										"localhost"
									],
									"port": "1337",
									"path": [
										"cart"
									]
								}
							},
							"status": "OK",
							"code": 200,
							"_postman_previewlanguage": "json",
							"header": [
								{
									"key": "X-Powered-By",
									"value": "Sails <sailsjs.com>"
								},
								{
									"key": "Content-Type",
									"value": "application/json; charset=utf-8"
								},
								{
									"key": "Content-Length",
									"value": "42"
								},
								{
									"key": "ETag",
									"value": "W/\"2a-yrl/DysoQWxV+zfaB9dwEiZSzA8\""
								},
								{
									"key": "Date",
									"value": "Mon, 04 Mar 2024 10:00:53 GMT"
								},
								{
									"key": "Connection",
									"value": "keep-alive"
								},
								{
									"key": "Keep-Alive",
									"value": "timeout=5"
								}
							],
							"cookie": [],
							"body": "\"Product was added into cart successfully\""
						}
					]
				},
				{
					"name": "Checkout",
					"request": {
						"method": "GET",
						"header": [],
						"url": {
							"raw": "http://localhost:1337/checkout",
							"protocol": "http",
							"host": [
								"localhost"
							],
							"port": "1337",
							"path": [
								"checkout"
							]
						}
					},
					"response": [
						{
							"name": "success",
							"originalRequest": {
								"method": "GET",
								"header": [],
								"url": {
									"raw": "http://localhost:1337/checkout",
									"protocol": "http",
									"host": [
										"localhost"
									],
									"port": "1337",
									"path": [
										"checkout"
									]
								}
							},
							"status": "OK",
							"code": 200,
							"_postman_previewlanguage": "json",
							"header": [
								{
									"key": "X-Powered-By",
									"value": "Sails <sailsjs.com>"
								},
								{
									"key": "Content-Type",
									"value": "application/json; charset=utf-8"
								},
								{
									"key": "Content-Length",
									"value": "23"
								},
								{
									"key": "ETag",
									"value": "W/\"17-tAy3AhWtAquFWwJoBAHEYyYP+6g\""
								},
								{
									"key": "Date",
									"value": "Mon, 04 Mar 2024 10:03:20 GMT"
								},
								{
									"key": "Connection",
									"value": "keep-alive"
								},
								{
									"key": "Keep-Alive",
									"value": "timeout=5"
								}
							],
							"cookie": [],
							"body": "{\n    \"TotalPay\": 30000\n}"
						}
					]
				},
				{
					"name": "Home",
					"request": {
						"method": "GET",
						"header": [],
						"url": {
							"raw": "http://localhost:1337",
							"protocol": "http",
							"host": [
								"localhost"
							],
							"port": "1337"
						}
					},
					"response": [
						{
							"name": "Success",
							"originalRequest": {
								"method": "GET",
								"header": [],
								"url": {
									"raw": "http://localhost:1337",
									"protocol": "http",
									"host": [
										"localhost"
									],
									"port": "1337"
								}
							},
							"status": "OK",
							"code": 200,
							"_postman_previewlanguage": "json",
							"header": [
								{
									"key": "X-Powered-By",
									"value": "Sails <sailsjs.com>"
								},
								{
									"key": "Content-Type",
									"value": "application/json; charset=utf-8"
								},
								{
									"key": "Content-Length",
									"value": "1667"
								},
								{
									"key": "ETag",
									"value": "W/\"683-5ve641QHrqWkAeVQ3e0loo60M38\""
								},
								{
									"key": "Date",
									"value": "Mon, 04 Mar 2024 13:22:40 GMT"
								},
								{
									"key": "Connection",
									"value": "keep-alive"
								},
								{
									"key": "Keep-Alive",
									"value": "timeout=5"
								}
							],
							"cookie": [],
							"body": "[\n    {\n        \"createdAt\": 1709546356028,\n        \"updatedAt\": 1709546356028,\n        \"id\": \"65e59b7493605124c39f30ce\",\n        \"title\": \"Mobile\",\n        \"imageUrl\": \"https://5.imimg.com/data5/SELLER/Default/2020/12/WI/VR/VK/118676901/oppo-f17-pro-mobile.jpg\",\n        \"price\": 10000,\n        \"description\": \"abcdefghijklmnopqrstuv\",\n        \"category\": \"Elec\"\n    },\n    {\n        \"createdAt\": 1709546356646,\n        \"updatedAt\": 1709546356646,\n        \"id\": \"65e59b7493605124c39f30cf\",\n        \"title\": \"Mobile\",\n        \"imageUrl\": \"https://5.imimg.com/data5/SELLER/Default/2020/12/WI/VR/VK/118676901/oppo-f17-pro-mobile.jpg\",\n        \"price\": 10000,\n        \"description\": \"abcdefghijklmnopqrstuv\",\n        \"category\": \"Elec\"\n    },\n    {\n        \"createdAt\": 1709546357260,\n        \"updatedAt\": 1709546357260,\n        \"id\": \"65e59b7593605124c39f30d0\",\n        \"title\": \"Mobile\",\n        \"imageUrl\": \"https://5.imimg.com/data5/SELLER/Default/2020/12/WI/VR/VK/118676901/oppo-f17-pro-mobile.jpg\",\n        \"price\": 10000,\n        \"description\": \"abcdefghijklmnopqrstuv\",\n        \"category\": \"Elec\"\n    },\n    {\n        \"createdAt\": 1709552300005,\n        \"updatedAt\": 1709552300005,\n        \"id\": \"65e5b2ac33511448695b7b2d\",\n        \"title\": \"Mobile\",\n        \"imageUrl\": \"https://5.imimg.com/data5/SELLER/Default/2020/12/WI/VR/VK/118676901/oppo-f17-pro-mobile.jpg\",\n        \"price\": 10000,\n        \"description\": \"abcdefghijklmnopqrstuv\",\n        \"category\": \"Elec\"\n    },\n    {\n        \"createdAt\": 1709553164574,\n        \"updatedAt\": 1709553264548,\n        \"id\": \"65e5b60cfc20281b33624c31\",\n        \"title\": \"Mobile\",\n        \"imageUrl\": \"https://5.imimg.com/data5/SELLER/Default/2020/12/WI/VR/VK/118676901/oppo-f17-pro-mobile.jpg\",\n        \"price\": 21212,\n        \"description\": \"abcdefghijklmnopqrstuv\",\n        \"category\": \"Elec\"\n    }\n]"
						}
					]
				},
				{
					"name": "Products",
					"request": {
						"method": "GET",
						"header": []
					},
					"response": [
						{
							"name": "success",
							"originalRequest": {
								"method": "GET",
								"header": [],
								"url": {
									"raw": "http://localhost:1337/products",
									"protocol": "http",
									"host": [
										"localhost"
									],
									"port": "1337",
									"path": [
										"products"
									]
								}
							},
							"status": "OK",
							"code": 200,
							"_postman_previewlanguage": "json",
							"header": [
								{
									"key": "X-Powered-By",
									"value": "Sails <sailsjs.com>"
								},
								{
									"key": "Content-Type",
									"value": "application/json; charset=utf-8"
								},
								{
									"key": "Content-Length",
									"value": "1667"
								},
								{
									"key": "ETag",
									"value": "W/\"683-5ve641QHrqWkAeVQ3e0loo60M38\""
								},
								{
									"key": "Set-Cookie",
									"value": "connect.sid=s%3ArfCAnzQeLnirNL2fCH08tr17ybGEasjl.sqh4vt8741qKkVDb8d7qvuwKehqmnc%2FaHkwpV14KElo; Path=/; Expires=Wed, 06 Mar 2024 04:45:01 GMT; HttpOnly"
								},
								{
									"key": "Date",
									"value": "Tue, 05 Mar 2024 04:45:01 GMT"
								},
								{
									"key": "Connection",
									"value": "keep-alive"
								},
								{
									"key": "Keep-Alive",
									"value": "timeout=5"
								}
							],
							"cookie": [],
							"body": "[\n    {\n        \"createdAt\": 1709546356028,\n        \"updatedAt\": 1709546356028,\n        \"id\": \"65e59b7493605124c39f30ce\",\n        \"title\": \"Mobile\",\n        \"imageUrl\": \"https://5.imimg.com/data5/SELLER/Default/2020/12/WI/VR/VK/118676901/oppo-f17-pro-mobile.jpg\",\n        \"price\": 10000,\n        \"description\": \"abcdefghijklmnopqrstuv\",\n        \"category\": \"Elec\"\n    },\n    {\n        \"createdAt\": 1709546356646,\n        \"updatedAt\": 1709546356646,\n        \"id\": \"65e59b7493605124c39f30cf\",\n        \"title\": \"Mobile\",\n        \"imageUrl\": \"https://5.imimg.com/data5/SELLER/Default/2020/12/WI/VR/VK/118676901/oppo-f17-pro-mobile.jpg\",\n        \"price\": 10000,\n        \"description\": \"abcdefghijklmnopqrstuv\",\n        \"category\": \"Elec\"\n    },\n    {\n        \"createdAt\": 1709546357260,\n        \"updatedAt\": 1709546357260,\n        \"id\": \"65e59b7593605124c39f30d0\",\n        \"title\": \"Mobile\",\n        \"imageUrl\": \"https://5.imimg.com/data5/SELLER/Default/2020/12/WI/VR/VK/118676901/oppo-f17-pro-mobile.jpg\",\n        \"price\": 10000,\n        \"description\": \"abcdefghijklmnopqrstuv\",\n        \"category\": \"Elec\"\n    },\n    {\n        \"createdAt\": 1709552300005,\n        \"updatedAt\": 1709552300005,\n        \"id\": \"65e5b2ac33511448695b7b2d\",\n        \"title\": \"Mobile\",\n        \"imageUrl\": \"https://5.imimg.com/data5/SELLER/Default/2020/12/WI/VR/VK/118676901/oppo-f17-pro-mobile.jpg\",\n        \"price\": 10000,\n        \"description\": \"abcdefghijklmnopqrstuv\",\n        \"category\": \"Elec\"\n    },\n    {\n        \"createdAt\": 1709553164574,\n        \"updatedAt\": 1709553264548,\n        \"id\": \"65e5b60cfc20281b33624c31\",\n        \"title\": \"Mobile\",\n        \"imageUrl\": \"https://5.imimg.com/data5/SELLER/Default/2020/12/WI/VR/VK/118676901/oppo-f17-pro-mobile.jpg\",\n        \"price\": 21212,\n        \"description\": \"abcdefghijklmnopqrstuv\",\n        \"category\": \"Elec\"\n    }\n]"
						}
					]
				},
				{
					"name": "Single Product",
					"request": {
						"method": "GET",
						"header": []
					},
					"response": [
						{
							"name": "success",
							"originalRequest": {
								"method": "GET",
								"header": [],
								"url": {
									"raw": "http://localhost:1337/products/65e59b7493605124c39f30ce",
									"protocol": "http",
									"host": [
										"localhost"
									],
									"port": "1337",
									"path": [
										"products",
										"65e59b7493605124c39f30ce"
									]
								}
							},
							"status": "OK",
							"code": 200,
							"_postman_previewlanguage": "json",
							"header": [
								{
									"key": "X-Powered-By",
									"value": "Sails <sailsjs.com>"
								},
								{
									"key": "Content-Type",
									"value": "application/json; charset=utf-8"
								},
								{
									"key": "Content-Length",
									"value": "311"
								},
								{
									"key": "ETag",
									"value": "W/\"137-jb8ih8wHT67AZdHl9NABT2pQxEo\""
								},
								{
									"key": "Date",
									"value": "Tue, 05 Mar 2024 04:46:08 GMT"
								},
								{
									"key": "Connection",
									"value": "keep-alive"
								},
								{
									"key": "Keep-Alive",
									"value": "timeout=5"
								}
							],
							"cookie": [],
							"body": "{\n    \"createdAt\": 1709546356028,\n    \"updatedAt\": 1709546356028,\n    \"id\": \"65e59b7493605124c39f30ce\",\n    \"title\": \"Mobile\",\n    \"imageUrl\": \"https://5.imimg.com/data5/SELLER/Default/2020/12/WI/VR/VK/118676901/oppo-f17-pro-mobile.jpg\",\n    \"price\": 10000,\n    \"description\": \"abcdefghijklmnopqrstuv\",\n    \"category\": \"Elec\"\n}"
						}
					]
				},
				{
					"name": "Delete cart",
					"request": {
						"method": "POST",
						"header": [],
						"body": {
							"mode": "raw",
							"raw": "{\n    \"productId\":\"65e6a3f4d3082b56c4952467\"\n}",
							"options": {
								"raw": {
									"language": "json"
								}
							}
						},
						"url": {
							"raw": "http://localhost:1337/deletecart",
							"protocol": "http",
							"host": [
								"localhost"
							],
							"port": "1337",
							"path": [
								"deletecart"
							]
						}
					},
					"response": [
						{
							"name": "success",
							"originalRequest": {
								"method": "POST",
								"header": [],
								"body": {
									"mode": "raw",
									"raw": "{\n    \"productId\":\"65e6a3f4d3082b56c4952467\"\n}",
									"options": {
										"raw": {
											"language": "json"
										}
									}
								},
								"url": {
									"raw": "http://localhost:1337/deletecart",
									"protocol": "http",
									"host": [
										"localhost"
									],
									"port": "1337",
									"path": [
										"deletecart"
									]
								}
							},
							"status": "Not Found",
							"code": 404,
							"_postman_previewlanguage": "json",
							"header": [
								{
									"key": "X-Powered-By",
									"value": "Sails <sailsjs.com>"
								},
								{
									"key": "Content-Type",
									"value": "application/json; charset=utf-8"
								},
								{
									"key": "Content-Length",
									"value": "37"
								},
								{
									"key": "ETag",
									"value": "W/\"25-WQBoAaNLZ/f6g6wMU9uAdm0VM1c\""
								},
								{
									"key": "Set-Cookie",
									"value": "connect.sid=s%3AFZKiexfsdEKaIGnIiVDe0vrcXkAWCYc6.MhH8aXVpxyN4I5PGHN12dn9Vaej8C6jvScy5QoPjNpY; Path=/; Expires=Wed, 06 Mar 2024 04:49:52 GMT; HttpOnly"
								},
								{
									"key": "Date",
									"value": "Tue, 05 Mar 2024 04:49:52 GMT"
								},
								{
									"key": "Connection",
									"value": "keep-alive"
								},
								{
									"key": "Keep-Alive",
									"value": "timeout=5"
								}
							],
							"cookie": [],
							"body": "{\n    \"error\": \"Product is Not found\"\n}"
						}
					]
				}
			]
		},
		{
			"name": "Admin",
			"item": [
				{
					"name": "Add-Prooduct",
					"request": {
						"method": "POST",
						"header": [],
						"body": {
							"mode": "raw",
							"raw": "{\n    \"title\":\"Mobile\",\n    \"imageUrl\":\"https://5.imimg.com/data5/SELLER/Default/2020/12/WI/VR/VK/118676901/oppo-f17-pro-mobile.jpg\",\n    \"price\":10000,\n    \"description\":\"abcdefghijklmnopqrstuv\",\n    \"category\":\"Elec\"\n}",
							"options": {
								"raw": {
									"language": "json"
								}
							}
						},
						"url": {
							"raw": "http://localhost:1337/admin/add-product",
							"protocol": "http",
							"host": [
								"localhost"
							],
							"port": "1337",
							"path": [
								"admin",
								"add-product"
							]
						}
					},
					"response": [
						{
							"name": "success",
							"originalRequest": {
								"method": "POST",
								"header": [],
								"body": {
									"mode": "raw",
									"raw": "{\n    \"title\":\"Mobile\",\n    \"imageUrl\":\"https://5.imimg.com/data5/SELLER/Default/2020/12/WI/VR/VK/118676901/oppo-f17-pro-mobile.jpg\",\n    \"price\":10000,\n    \"description\":\"abcdefghijklmnopqrstuv\",\n    \"category\":\"Elec\"\n}",
									"options": {
										"raw": {
											"language": "json"
										}
									}
								},
								"url": {
									"raw": "http://localhost:1337/admin/add-product",
									"protocol": "http",
									"host": [
										"localhost"
									],
									"port": "1337",
									"path": [
										"admin",
										"add-product"
									]
								}
							},
							"status": "OK",
							"code": 200,
							"_postman_previewlanguage": "json",
							"header": [
								{
									"key": "X-Powered-By",
									"value": "Sails <sailsjs.com>"
								},
								{
									"key": "Content-Type",
									"value": "application/json; charset=utf-8"
								},
								{
									"key": "Content-Length",
									"value": "32"
								},
								{
									"key": "ETag",
									"value": "W/\"20-YJVRHecDbu83qbPQNb/KlEd/ocs\""
								},
								{
									"key": "Date",
									"value": "Mon, 04 Mar 2024 09:46:34 GMT"
								},
								{
									"key": "Connection",
									"value": "keep-alive"
								},
								{
									"key": "Keep-Alive",
									"value": "timeout=5"
								}
							],
							"cookie": [],
							"body": "\"Product was added successfully\""
						}
					]
				},
				{
					"name": "Edit-product",
					"request": {
						"method": "POST",
						"header": [],
						"body": {
							"mode": "raw",
							"raw": "{\n    \"productId\":\"65e5986a7ff504a01b4a1547\",\n    \"title\":\"Mobile\",\n    \"imageUrl\":\"https://5.imimg.com/data5/SELLER/Default/2020/12/WI/VR/VK/118676901/oppo-f17-pro-mobile.jpg\",\n    \"price\":110000,\n    \"description\":\"abcdefghijklmnopqrstuv\",\n    \"category\":\"Elec\"\n}",
							"options": {
								"raw": {
									"language": "json"
								}
							}
						},
						"url": {
							"raw": "http://localhost:1337/admin/edit-product",
							"protocol": "http",
							"host": [
								"localhost"
							],
							"port": "1337",
							"path": [
								"admin",
								"edit-product"
							]
						}
					},
					"response": [
						{
							"name": "success",
							"originalRequest": {
								"method": "POST",
								"header": [],
								"body": {
									"mode": "raw",
									"raw": "{\n    \"productId\":\"65e5986a7ff504a01b4a1547\",\n    \"title\":\"Mobile\",\n    \"imageUrl\":\"https://5.imimg.com/data5/SELLER/Default/2020/12/WI/VR/VK/118676901/oppo-f17-pro-mobile.jpg\",\n    \"price\":110000,\n    \"description\":\"abcdefghijklmnopqrstuv\",\n    \"category\":\"Elec\"\n}",
									"options": {
										"raw": {
											"language": "json"
										}
									}
								},
								"url": {
									"raw": "http://localhost:1337/admin/edit-product",
									"protocol": "http",
									"host": [
										"localhost"
									],
									"port": "1337",
									"path": [
										"admin",
										"edit-product"
									]
								}
							},
							"status": "OK",
							"code": 200,
							"_postman_previewlanguage": "json",
							"header": [
								{
									"key": "X-Powered-By",
									"value": "Sails <sailsjs.com>"
								},
								{
									"key": "Content-Type",
									"value": "application/json; charset=utf-8"
								},
								{
									"key": "Content-Length",
									"value": "33"
								},
								{
									"key": "ETag",
									"value": "W/\"21-Ox2xrlnD36O4ddw4jFcD6BtFotg\""
								},
								{
									"key": "Date",
									"value": "Mon, 04 Mar 2024 09:52:47 GMT"
								},
								{
									"key": "Connection",
									"value": "keep-alive"
								},
								{
									"key": "Keep-Alive",
									"value": "timeout=5"
								}
							],
							"cookie": [],
							"body": "\"Product was edited successfully\""
						}
					]
				},
				{
					"name": "Delete-Product",
					"request": {
						"method": "POST",
						"header": [],
						"body": {
							"mode": "raw",
							"raw": "{\n    \"productId\":\"65e5986a7ff504a01b4a1547\"\n}",
							"options": {
								"raw": {
									"language": "json"
								}
							}
						},
						"url": {
							"raw": "http://localhost:1337/admin/delete-product",
							"protocol": "http",
							"host": [
								"localhost"
							],
							"port": "1337",
							"path": [
								"admin",
								"delete-product"
							]
						}
					},
					"response": [
						{
							"name": "success",
							"originalRequest": {
								"method": "POST",
								"header": [],
								"body": {
									"mode": "raw",
									"raw": "{\n    \"productId\":\"65e5986a7ff504a01b4a1547\"\n}",
									"options": {
										"raw": {
											"language": "json"
										}
									}
								},
								"url": {
									"raw": "http://localhost:1337/admin/delete-product",
									"protocol": "http",
									"host": [
										"localhost"
									],
									"port": "1337",
									"path": [
										"admin",
										"delete-product"
									]
								}
							},
							"status": "OK",
							"code": 200,
							"_postman_previewlanguage": "json",
							"header": [
								{
									"key": "X-Powered-By",
									"value": "Sails <sailsjs.com>"
								},
								{
									"key": "Content-Type",
									"value": "application/json; charset=utf-8"
								},
								{
									"key": "Content-Length",
									"value": "34"
								},
								{
									"key": "ETag",
									"value": "W/\"22-XdRLAb2N5iLcXQmWIkYwUkTt+kw\""
								},
								{
									"key": "Date",
									"value": "Mon, 04 Mar 2024 09:56:48 GMT"
								},
								{
									"key": "Connection",
									"value": "keep-alive"
								},
								{
									"key": "Keep-Alive",
									"value": "timeout=5"
								}
							],
							"cookie": [],
							"body": "\"Product was deleted successfully\""
						}
					]
				}
			]
		}
	]
}